pycopy.py
pycopy_imphook.py
setup.py
pycopy_cpython_pycopy.egg-info/PKG-INFO
pycopy_cpython_pycopy.egg-info/SOURCES.txt
pycopy_cpython_pycopy.egg-info/dependency_links.txt
pycopy_cpython_pycopy.egg-info/requires.txt
pycopy_cpython_pycopy.egg-info/top_level.txt