Metadata-Version: 1.2
Name: pycopy-cpython-pycopy
Version: 0.4
Summary: Pycopy module pycopy ported to CPython
Home-page: https://github.com/pfalcon/pycopy-lib
Author: Paul Sokolovsky
Author-email: pycopy-dev@googlegroups.com
Maintainer: Paul Sokolovsky
Maintainer-email: pycopy-dev@googlegroups.com
License: MIT
Platform: UNKNOWN
